sql2erd/__init__.py
sql2erd/__main__.py
sql2erd/main.py
sql2erd/sql2erd.py
sql2erd-0.1.1.dist-info/LICENSE
sql2erd-0.1.1.dist-info/METADATA
sql2erd-0.1.1.dist-info/WHEEL
sql2erd-0.1.1.dist-info/entry_points.txt
sql2erd-0.1.1.dist-info/top_level.txt
sql2erd-0.1.1.dist-info/RECORD
