Metadata-Version: 2.1
Name: sql2erd
Version: 0.1.1
Summary: Transforms a .sql file of CREATE TABLE statments into an ERD using Graphviz
Author-email: mhdeeb <s-mohamed.eldeeb@zewailcity.edu.eg>
License: MIT License
Project-URL: Source, https://github.com/mhdeeb/sql2erd
Classifier: Programming Language :: Python :: 3
Classifier: License :: OSI Approved :: MIT License
Classifier: Operating System :: OS Independent
Requires-Python: >=3.9
License-File: LICENSE
Requires-Dist: graphviz
Requires-Dist: sqlparse
